.gitignore
CONTRIBUTING.md
LICENSE
MANIFEST.in
README.md
environment.yml
pyproject.toml
requirements.txt
setup.cfg
setup.py
version.txt
.github/ISSUE_TEMPLATE/bug_report.md
.github/ISSUE_TEMPLATE/feature_request.md
earth_vision.egg-info/PKG-INFO
earth_vision.egg-info/SOURCES.txt
earth_vision.egg-info/dependency_links.txt
earth_vision.egg-info/requires.txt
earth_vision.egg-info/top_level.txt
earthvision/__init__.py
earthvision/dataset.py
earthvision/constants/__init__.py
earthvision/constants/COWC/__init__.py
earthvision/constants/COWC/config.py
earthvision/constants/DroneDeploy/__init__.py
earthvision/constants/DroneDeploy/config.py
earthvision/constants/L7Irish/source.yaml
earthvision/constants/L8Biome/source.yaml
earthvision/constants/L8Sparcs/source.yaml
earthvision/constants/RESISC45/__init__.py
earthvision/constants/RESISC45/config.py
earthvision/constants/XView/__init__.py
earthvision/constants/XView/config.py
earthvision/datasets/95cloud.py
earthvision/datasets/__init__.py
earthvision/datasets/aerialcactus.py
earthvision/datasets/bigearthnet.py
earthvision/datasets/cloud38.py
earthvision/datasets/cowc.py
earthvision/datasets/deepsat.py
earthvision/datasets/drone_deploy.py
earthvision/datasets/eurosat.py
earthvision/datasets/l7irish.py
earthvision/datasets/l8biome.py
earthvision/datasets/l8sparcs.py
earthvision/datasets/landcover.py
earthvision/datasets/landcovernet.py
earthvision/datasets/neon.py
earthvision/datasets/resisc45.py
earthvision/datasets/sentinel2cloud.py
earthvision/datasets/skyscapes.py
earthvision/datasets/so2sat.py
earthvision/datasets/spacenet7.py
earthvision/datasets/spacenet7_utils.py
earthvision/datasets/ucmercedland.py
earthvision/datasets/utils.py
earthvision/datasets/vision.py
earthvision/datasets/xview.py
earthvision/models/README.md
earthvision/models/__init__.py
earthvision/models/how_to_use_vit.md
earthvision/models/resisc45/__init__.py
earthvision/models/resisc45/coatnet.py
earthvision/models/resisc45/mobilenetv3.py
earthvision/models/resisc45/regnet.py
earthvision/models/resisc45/resnet.py
earthvision/models/resisc45/utils.py
earthvision/models/resisc45/vgg16.py