Metadata-Version: 2.1
Name: earth-vision
Version: 1.0.0
Summary: Python library for solving computer vision tasks specifically for satellite imagery
Home-page: https://github.com/jakartaresearch/earth-vision
Author: Jakarta Research Team
Author-email: researchjair@gmail.com
License: MIT
Download-URL: https://github.com/jakartaresearch/earth-vision/archive/v1.0.0.tar.gz
Keywords: computer-vision,pytorch,machine-learning,satellite-imagery
Platform: UNKNOWN
Classifier: Development Status :: 3 - Alpha
Classifier: Intended Audience :: Developers
Classifier: Topic :: Scientific/Engineering :: Artificial Intelligence
Classifier: Topic :: Software Development :: Libraries
Classifier: Topic :: Software Development :: Libraries :: Python Modules
Classifier: License :: OSI Approved :: MIT License
Classifier: Programming Language :: Python :: 3.7
Classifier: Programming Language :: Python :: 3.8
Classifier: Programming Language :: Python :: 3.9
License-File: LICENSE
